setup.py
xcodearchive/AssetCarAnalysis.py
xcodearchive/AutoPackage.py
xcodearchive/__init__.py
xcodearchive/pick.py
xcodearchive/xcodetool.py
xcodearchive.egg-info/PKG-INFO
xcodearchive.egg-info/SOURCES.txt
xcodearchive.egg-info/dependency_links.txt
xcodearchive.egg-info/entry_points.txt
xcodearchive.egg-info/top_level.txt