Metadata-Version: 1.1
Name: xcodearchive
Version: 1.5.0
Summary: A  xcode build and archive tools
Home-page: https://github.com/zhipengbird/xcode_archive
Author: yuanpinghua
Author-email: yuanpinghua@yeah.net
License: MIT
Keywords: xcode,build,archive
Platform: UNKNOWN
Classifier: Development Status :: 4 - Beta
Classifier: Intended Audience :: Developers
Classifier: License :: OSI Approved :: MIT License
Classifier: Programming Language :: Python
Classifier: Programming Language :: Python :: 2.6
Classifier: Programming Language :: Python :: 2.7
Classifier: Programming Language :: Python :: 3.3
